gec_datasets/__init__.py
gec_datasets/datasets.py
gec_datasets/datasets_test.py
gec_datasets/cli/available.py
gec_datasets/cli/download.py
gec_datasets/downloaders/__init__.py
gec_datasets/downloaders/base.py
gec_datasets/downloaders/conll13.py
gec_datasets/downloaders/conll14.py
gec_datasets/downloaders/cweb.py
gec_datasets/downloaders/fce.py
gec_datasets/downloaders/jfleg.py
gec_datasets/downloaders/lang8.py
gec_datasets/downloaders/nucle.py
gec_datasets/downloaders/pie_synthetic.py
gec_datasets/downloaders/troy_1bw.py
gec_datasets/downloaders/troy_blogs.py
gec_datasets/downloaders/wi_locness.py
gec_datasets-0.2.0.dist-info/METADATA
gec_datasets-0.2.0.dist-info/WHEEL
gec_datasets-0.2.0.dist-info/entry_points.txt
gec_datasets-0.2.0.dist-info/licenses/LICENSE
gec_datasets-0.2.0.dist-info/RECORD
