Metadata-Version: 2.4
Name: gec-datasets
Version: 0.2.0
Summary: A tools to easily load Grammatical Error Correction datasets.
Author: gotuiyan
License-File: LICENSE
Requires-Python: >=3.11.0
Requires-Dist: gdown>=5.2.0
Requires-Dist: gecommon>=0.1.0
Requires-Dist: requests>=2.32.3
